mlnext/__init__.py
mlnext/anomaly.py
mlnext/data.py
mlnext/io.py
mlnext/model.py
mlnext/pipeline.py
mlnext/plot.py
mlnext/py.typed
mlnext/score.py
mlnext/utils.py
mlnext_framework-0.6.1.dist-info/METADATA
mlnext_framework-0.6.1.dist-info/WHEEL
mlnext_framework-0.6.1.dist-info/licenses/LICENSE
mlnext_framework-0.6.1.dist-info/RECORD
