Metadata-Version: 2.3
Name: mlnext-framework
Version: 0.6.1
Summary: Machine learning utilities.
Project-URL: Repository, https://github.com/PLCnext/MLnext-Framework
Project-URL: Documentation, https://mlnext-framework.readthedocs.io/en/latest/
Author-email: PHOENIX CONTACT Electronics GmbH <digitalfactorynow@phoenixcontact.com>, Gorden Platz <gplatz@phoenixcontact.com>
Keywords: learning,machine,mlnext,utilities
Classifier: Intended Audience :: Developers
Classifier: Operating System :: OS Independent
Classifier: Programming Language :: Python :: 3.9
Classifier: Programming Language :: Python :: 3.10
Classifier: Programming Language :: Python :: 3.11
Classifier: Programming Language :: Python :: 3.12
Classifier: Programming Language :: Python :: 3.13
Classifier: Topic :: Scientific/Engineering :: Artificial Intelligence
Classifier: Topic :: Scientific/Engineering :: Visualization
Classifier: Topic :: Software Development :: Libraries
Requires-Python: >=3.9
Requires-Dist: matplotlib>=3.5.0
Requires-Dist: numpy>=1.21.4
Requires-Dist: pandas>=1.2.3
Requires-Dist: pydantic>=1.8.1
Requires-Dist: pydeprecate>=0.3.2
Requires-Dist: pydot>=1.4.2
Requires-Dist: pyyaml>=5.4.1
Requires-Dist: scikit-learn>=0.24.1
Requires-Dist: seaborn>=0.11
Provides-Extra: docs
Requires-Dist: furo>=2024.01.29; extra == 'docs'
Requires-Dist: myst-parser>=2.0.0; extra == 'docs'
Requires-Dist: numpydoc>=1.7.0; extra == 'docs'
Requires-Dist: python-dateutil>=2.8.2; extra == 'docs'
Requires-Dist: rinohtype>=0.5.4; extra == 'docs'
Requires-Dist: sphinx-copybutton>=0.5.2; extra == 'docs'
Requires-Dist: sphinx>=7.2.6; extra == 'docs'
Provides-Extra: tests
Requires-Dist: coverage>=7.5.3; extra == 'tests'
Requires-Dist: pytest>=8.2.2; extra == 'tests'
Requires-Dist: scipy>=1.10.1; extra == 'tests'
Requires-Dist: testfixtures>=8.3.0; extra == 'tests'
